interactiveTutorial/CreateTutorial.py
interactiveTutorial/GUIDE.pdf
interactiveTutorial/RunTutorial.py
interactiveTutorial/TutorialMenu.py
interactiveTutorial/_TestProgram.py
interactiveTutorial/_TutorialBase.py
interactiveTutorial/__init__.py
interactiveTutorial/testTutorials/0_Introduction.pyz
interactiveTutorial/testTutorials/1_Example.pyz
interactiveTutorial/testTutorials/2_UsingTheEditor.pyz
interactiveTutorial-0.1.1.dist-info/DESCRIPTION.rst
interactiveTutorial-0.1.1.dist-info/METADATA
interactiveTutorial-0.1.1.dist-info/RECORD
interactiveTutorial-0.1.1.dist-info/WHEEL
interactiveTutorial-0.1.1.dist-info/metadata.json
interactiveTutorial-0.1.1.dist-info/top_level.txt
