Metadata-Version: 2.0
Name: interactiveTutorial
Version: 0.1.1
Summary: 
Requires-Dist: fancytools (>=0.2.0)
Requires-Dist: fancywidgets (>=0.1.0)
